fipe/__init__.py
fipe/fipe.py
fipe/mip.py
fipe/oracle.py
fipe/typing.py
fipe/ensemble/__init__.py
fipe/ensemble/builder.py
fipe/ensemble/container.py
fipe/ensemble/ensemble.py
fipe/ensemble/binders/__init__.py
fipe/ensemble/binders/binder.py
fipe/ensemble/binders/boost.py
fipe/ensemble/binders/callback.py
fipe/ensemble/binders/lgbm.py
fipe/ensemble/binders/sklearn.py
fipe/ensemble/binders/xgb.py
fipe/ensemble/parsers/__init__.py
fipe/ensemble/parsers/lgbm.py
fipe/ensemble/parsers/parser.py
fipe/ensemble/parsers/sklearn.py
fipe/ensemble/parsers/xgb.py
fipe/feature/__init__.py
fipe/feature/container.py
fipe/feature/encoder.py
fipe/feature/variables/__init__.py
fipe/feature/variables/binary.py
fipe/feature/variables/categorical.py
fipe/feature/variables/continuous.py
fipe/feature/variables/feature.py
fipe/flow/__init__.py
fipe/flow/variables.py
fipe/ocean/__init__.py
fipe/ocean/base.py
fipe/ocean/ocean.py
fipe/ocean/parsers.py
fipe/prune/__init__.py
fipe/prune/base.py
fipe/prune/pruner.py
fipe/tree/__init__.py
fipe/tree/container.py
fipe/tree/tree.py
fipepy-1.0.7.dist-info/LICENSE
fipepy-1.0.7.dist-info/METADATA
fipepy-1.0.7.dist-info/WHEEL
fipepy-1.0.7.dist-info/top_level.txt
fipepy-1.0.7.dist-info/RECORD
