Metadata-Version: 2.1
Name: fipepy
Version: 1.0.7
Summary: A simple Python package for Funcationally-Identical Pruning of Ensemble models
Author-email: Youssouf Emine <youssouf.emine@polymtl.ca>, Alexandre Forel <alexandre.forel@polymtl.ca>
License: MIT License
Project-URL: Homepage, https://github.com/eminyous/fipe
Project-URL: Repository, https://github.com/eminyous/fipe
Project-URL: Issues, https://github.com/eminyous/fipe/issues
Classifier: Development Status :: 4 - Beta
Classifier: Intended Audience :: Developers
Classifier: License :: OSI Approved :: MIT License
Classifier: Topic :: Software Development :: Libraries
Classifier: Programming Language :: Python :: 3
Classifier: Programming Language :: Python :: 3.12
Classifier: Programming Language :: Python :: 3.13
Classifier: Programming Language :: Python :: 3 :: Only
Requires-Python: >=3.12
License-File: LICENSE
Requires-Dist: numpy
Requires-Dist: gurobipy
Requires-Dist: scikit-learn
Requires-Dist: pandas
Requires-Dist: lightgbm
Requires-Dist: xgboost
Provides-Extra: dev
Requires-Dist: coverage; extra == "dev"
Requires-Dist: pytest; extra == "dev"
Requires-Dist: pytest-cov; extra == "dev"
Requires-Dist: ruff; extra == "dev"
Requires-Dist: tox; extra == "dev"
Provides-Extra: test
Requires-Dist: coverage; extra == "test"
Requires-Dist: pytest; extra == "test"
Requires-Dist: pytest-cov; extra == "test"
Requires-Dist: ruff; extra == "test"
Requires-Dist: tox; extra == "test"
